src/__init__.py
src/config.py
src/main.py
src/server.py
src/auth/__init__.py
src/auth/middleware.py
src/auth/oauth_server.py
src/auth/wellknown.py
src/registry/__init__.py
src/registry/http_client.py
src/registry/mcp_client_manager.py
src/registry/server_registry.py
src/sandbox/__init__.py
src/skills/__init__.py
src/skills/matcher.py
src/skills/skill_manager.py
src/skills/presets/time_utils.yaml
src/skills/presets/travel.yaml
src/skills/presets/web_research.yaml
src/tools/__init__.py
src/tools/call_tool.py
src/tools/discover_servers.py
src/tools/execute_script.py
src/tools/get_skill.py
src/utils/__init__.py
src/utils/logger.py
uno_mcp-0.1.0.dist-info/METADATA
uno_mcp-0.1.0.dist-info/WHEEL
uno_mcp-0.1.0.dist-info/entry_points.txt
uno_mcp-0.1.0.dist-info/RECORD
