Metadata-Version: 2.4
Name: uno-mcp
Version: 0.1.0
Summary: Uno MCP Server - All-in-One MCP Gateway with Skills
Project-URL: Homepage, https://github.com/xray918/uno-mcp
Project-URL: Repository, https://github.com/xray918/uno-mcp
Project-URL: Documentation, https://github.com/xray918/uno-mcp#readme
Project-URL: Issues, https://github.com/xray918/uno-mcp/issues
Author-email: xray918 <xray918@example.com>
License: MIT
Keywords: agent,ai,gateway,llm,mcp,openai,skills
Classifier: Development Status :: 4 - Beta
Classifier: Intended Audience :: Developers
Classifier: License :: OSI Approved :: MIT License
Classifier: Programming Language :: Python :: 3
Classifier: Programming Language :: Python :: 3.11
Classifier: Programming Language :: Python :: 3.12
Classifier: Topic :: Scientific/Engineering :: Artificial Intelligence
Classifier: Topic :: Software Development :: Libraries :: Python Modules
Requires-Python: >=3.11
Requires-Dist: aiofiles>=23.2.0
Requires-Dist: httpx>=0.27.0
Requires-Dist: hypercorn>=0.16.0
Requires-Dist: mcp>=1.0.0
Requires-Dist: numpy>=1.26.0
Requires-Dist: openai>=1.10.0
Requires-Dist: pydantic-settings>=2.1.0
Requires-Dist: pydantic>=2.5.0
Requires-Dist: python-dotenv>=1.0.0
Requires-Dist: pyyaml>=6.0.0
Requires-Dist: quart-cors>=0.8.0
Requires-Dist: quart>=0.19.0
Provides-Extra: dev
Requires-Dist: black>=24.0.0; extra == 'dev'
Requires-Dist: isort>=5.13.0; extra == 'dev'
Requires-Dist: mypy>=1.8.0; extra == 'dev'
Requires-Dist: pytest-asyncio>=0.23.0; extra == 'dev'
Requires-Dist: pytest-cov>=4.1.0; extra == 'dev'
Requires-Dist: pytest>=7.4.0; extra == 'dev'
